{
  "title": "DiffUSE January Roadmapping ",
  "lastUpdated": "2026-01-14T19:54:47.438Z",
  "swimlanes": [
    {
      "id": "compute",
      "name": "Compute Infrastructure",
      "color": "#3B82F6",
      "order": 0
    },
    {
      "id": "md-modeling",
      "name": "Molecular Dynamics Modeling",
      "color": "#06B6D4",
      "order": 1
    },
    {
      "id": "ml-modeling",
      "name": "Machine Learning Modeling",
      "color": "#8B5CF6",
      "order": 2
    },
    {
      "id": "webapp",
      "name": "Web App Development",
      "color": "#10B981",
      "order": 3
    },
    {
      "id": "mdx2",
      "name": "Data Processing (MDx2)",
      "color": "#EC4899",
      "order": 4
    },
    {
      "id": "data-acquisition",
      "name": "Data Acquisition",
      "color": "#14B8A6",
      "order": 5
    },
    {
      "id": "encoding",
      "name": "Encoding",
      "color": "#F97316",
      "order": 6
    },
    {
      "id": "operations",
      "name": "Operations",
      "color": "#6366F1",
      "order": 7
    }
  ],
  "items": [
    {
      "type": "milestone",
      "title": "Meet with James (VP CEO), Michael, Moody, Justin, Joseph, Andy weekly",
      "stage": "short-term",
      "swimlaneId": "compute",
      "id": "d5kERaoC5p3FRJuPtWifw",
      "itemLastUpdated": "2026-01-14T19:13:51.764Z"
    },
    {
      "type": "milestone",
      "title": "Establish SOP for data sharing internally and externally",
      "stage": "short-term",
      "swimlaneId": "compute",
      "id": "dytiKdRNe54iQs63qhkW2",
      "itemLastUpdated": "2026-01-14T19:14:55.289Z",
      "enables": []
    },
    {
      "type": "goal",
      "title": "diffuse.app is consistent with FAIR-squared",
      "stage": "long-term",
      "swimlaneId": "compute",
      "id": "t0HC0aT5OduFiKeKlzExg",
      "itemLastUpdated": "2026-01-14T19:21:30.464Z",
      "description": "",
      "enables": [
        "hOBrGztGQVq6acMq-JhAQ"
      ]
    },
    {
      "type": "milestone",
      "title": "Implement AI copiloting to assist with development",
      "stage": "recent",
      "swimlaneId": "mdx2",
      "id": "m7nITf_xT9hjxNAV5h8r3",
      "itemLastUpdated": "2026-01-14T19:19:43.358Z"
    },
    {
      "type": "milestone",
      "title": "make mdx2 pip installable",
      "stage": "recent",
      "swimlaneId": "mdx2",
      "id": "LnZRI98yxf0TiCzAJ-isL",
      "itemLastUpdated": "2026-01-14T19:33:51.944Z",
      "isWin": true,
      "completed": true
    },
    {
      "type": "blocker",
      "title": "Established workflow for queue management with Prefect, socialized and accessible by all users",
      "stage": "short-term",
      "swimlaneId": "compute",
      "id": "hhsTojeIH_3zKMH5MPA4g",
      "itemLastUpdated": "2026-01-14T19:29:21.754Z",
      "blockerStatus": "open",
      "enables": [
        "_q2MgfyUCdARmONjaV8sz",
        "GBHsr-JjxoJlNZiM1feFg",
        "hOBrGztGQVq6acMq-JhAQ"
      ],
      "description": "",
      "subItems": [
        {
          "id": "fJRdGTmh3XfI6rUPzAWTx",
          "title": "Develop SOP for Prefect and queuing",
          "completed": false,
          "order": 0,
          "subStageId": "backlog"
        },
        {
          "id": "517SsBvWsGuf1IX25cSNK",
          "title": "Test SOP with poweruser",
          "completed": false,
          "order": 1,
          "subStageId": "backlog"
        },
        {
          "id": "ndErAgtsa598UgUkP89wd",
          "title": "Disseminate protocol",
          "completed": false,
          "order": 2,
          "subStageId": "backlog"
        }
      ],
      "subItemConfig": {
        "viewType": "tasks",
        "customStages": [
          {
            "id": "done",
            "label": "Done",
            "order": 0
          },
          {
            "id": "in-progress",
            "label": "In Progress",
            "order": 1
          },
          {
            "id": "up-next",
            "label": "Up Next",
            "order": 2
          },
          {
            "id": "backlog",
            "label": "Backlog",
            "order": 3
          }
        ],
        "customStatusTags": [
          {
            "id": "not-started",
            "label": "Not Started",
            "color": "#6B7280"
          },
          {
            "id": "in-progress",
            "label": "In Progress",
            "color": "#3B82F6"
          },
          {
            "id": "blocked",
            "label": "Blocked",
            "color": "#EF4444"
          },
          {
            "id": "in-review",
            "label": "In Review",
            "color": "#F59E0B"
          },
          {
            "id": "done",
            "label": "Done",
            "color": "#10B981"
          }
        ]
      }
    },
    {
      "type": "milestone",
      "title": "Connect basic data acquisition with Prefect workflow/SOP",
      "stage": "short-term",
      "swimlaneId": "data-acquisition",
      "id": "GBHsr-JjxoJlNZiM1feFg",
      "itemLastUpdated": "2026-01-14T19:22:07.469Z",
      "dependsOn": [
        "hhsTojeIH_3zKMH5MPA4g"
      ]
    },
    {
      "type": "milestone",
      "title": "Build out testing",
      "stage": "long-term",
      "swimlaneId": "mdx2",
      "id": "LeceKtgyt_L2wKQrbVOrq",
      "itemLastUpdated": "2026-01-14T19:27:14.301Z"
    },
    {
      "type": "goal",
      "title": "VM stability and queueing system",
      "stage": "short-term",
      "swimlaneId": "md-modeling",
      "id": "WYnZlkFqm6KSOguPBj-G-",
      "itemLastUpdated": "2026-01-14T19:28:20.038Z",
      "dependsOn": []
    },
    {
      "type": "goal",
      "title": "All raw and analyzed data sharing done on webapp with versioning and persistent identifiers",
      "stage": "long-term",
      "swimlaneId": "webapp",
      "id": "hOBrGztGQVq6acMq-JhAQ",
      "itemLastUpdated": "2026-01-14T19:30:53.836Z",
      "dependsOn": [
        "hhsTojeIH_3zKMH5MPA4g",
        "t0HC0aT5OduFiKeKlzExg"
      ]
    },
    {
      "type": "milestone",
      "title": "Connect mdx2 basic processing with Prefect workflow",
      "stage": "short-term",
      "swimlaneId": "mdx2",
      "id": "_q2MgfyUCdARmONjaV8sz",
      "itemLastUpdated": "2026-01-14T19:31:43.025Z",
      "dependsOn": [
        "hhsTojeIH_3zKMH5MPA4g"
      ]
    },
    {
      "type": "goal",
      "title": "Tested Mac1 + ADP-ribose (7TX0) simulation",
      "stage": "recent",
      "swimlaneId": "md-modeling",
      "id": "NNpBm8nj04xE6ij7u9ioc",
      "itemLastUpdated": "2026-01-14T19:33:45.901Z",
      "completed": true,
      "isWin": true,
      "links": [
        {
          "url": "https://docs.google.com/presentation/d/1_K_YZy8HRRqBXtKjI1603MV0NDKyU_x84DzRYyci-qQ/edit?slide=id.g3acf7975c30_0_11&pli=1#slide=id.g3acf7975c30_0_11",
          "label": "Slides from Modeling meeting 2026-01-09",
          "type": "gdoc",
          "id": "pPR62GVOHXikSdDlMNITX"
        }
      ],
      "enables": [
        "xcqT1fA8VBFtUNSUxaSUz"
      ]
    },
    {
      "type": "goal",
      "title": "Sampleworks: Implement model-agnostic biomolecular ensemble guidance with experimental data",
      "stage": "long-term",
      "swimlaneId": "ml-modeling",
      "id": "sZJpDiYewX3wcLcYMOrIe",
      "itemLastUpdated": "2026-01-14T19:45:16.358Z"
    },
    {
      "type": "goal",
      "title": "Demonstrated ability to improve MD diffraction",
      "stage": "short-term",
      "swimlaneId": "md-modeling",
      "id": "xcqT1fA8VBFtUNSUxaSUz",
      "itemLastUpdated": "2026-01-14T19:42:25.090Z",
      "dependsOn": [
        "NNpBm8nj04xE6ij7u9ioc"
      ],
      "subItemConfig": {
        "viewType": "kanban",
        "customStages": [
          {
            "id": "done",
            "label": "Done",
            "order": 0
          },
          {
            "id": "in-progress",
            "label": "In Progress",
            "order": 1
          },
          {
            "id": "up-next",
            "label": "Up Next",
            "order": 2
          },
          {
            "id": "backlog",
            "label": "Backlog",
            "order": 3
          }
        ],
        "customStatusTags": [
          {
            "id": "not-started",
            "label": "Not Started",
            "color": "#6B7280"
          },
          {
            "id": "in-progress",
            "label": "In Progress",
            "color": "#3B82F6"
          },
          {
            "id": "blocked",
            "label": "Blocked",
            "color": "#EF4444"
          },
          {
            "id": "in-review",
            "label": "In Review",
            "color": "#F59E0B"
          },
          {
            "id": "done",
            "label": "Done",
            "color": "#10B981"
          }
        ]
      },
      "subItems": [
        {
          "id": "bA0nGUCRkbd1EDG8Hy4EY",
          "title": "Mac1 + ADP ribose completed",
          "completed": true,
          "order": 0,
          "subStageId": "done"
        },
        {
          "id": "uYgwrfze3JLmZdbkxnVgr",
          "title": "Mac1 + ADP ribose with sorted waters diffuse simulation",
          "completed": false,
          "order": 1,
          "subStageId": "in-progress"
        },
        {
          "id": "TjKb7lf9D7y3nIQBXsxe6",
          "title": "Mac1 + ADPr calculation and analysis of improvement",
          "completed": false,
          "order": 3,
          "subStageId": "up-next"
        },
        {
          "id": "ud666GfCcRr971iO_JIQT",
          "title": "DHFR calculation and analysis of improvement",
          "completed": false,
          "order": 3,
          "subStageId": "up-next"
        }
      ]
    },
    {
      "type": "milestone",
      "title": "testing of another system and ability to improve: DHFR (7FPV) simulation",
      "stage": "short-term",
      "swimlaneId": "md-modeling",
      "id": "Hl751WCRo7VMsJsMuKJwE",
      "itemLastUpdated": "2026-01-14T19:39:19.139Z",
      "subItemConfig": {
        "viewType": "kanban",
        "customStages": [
          {
            "id": "done",
            "label": "Done",
            "order": 0
          },
          {
            "id": "in-progress",
            "label": "In Progress",
            "order": 1
          },
          {
            "id": "up-next",
            "label": "Up Next",
            "order": 2
          },
          {
            "id": "backlog",
            "label": "Backlog",
            "order": 3
          }
        ],
        "customStatusTags": [
          {
            "id": "not-started",
            "label": "Not Started",
            "color": "#6B7280"
          },
          {
            "id": "in-progress",
            "label": "In Progress",
            "color": "#3B82F6"
          },
          {
            "id": "blocked",
            "label": "Blocked",
            "color": "#EF4444"
          },
          {
            "id": "in-review",
            "label": "In Review",
            "color": "#F59E0B"
          },
          {
            "id": "done",
            "label": "Done",
            "color": "#10B981"
          }
        ]
      },
      "subItems": [
        {
          "id": "iR0X6CmQ4ubLL_onoNPuo",
          "title": "Restrained simulation",
          "completed": false,
          "order": 0,
          "subStageId": "in-progress"
        },
        {
          "id": "ZgBA4QqH0NpZifIOaCZP2",
          "title": "Unrestrained simulation",
          "completed": false,
          "order": 1,
          "subStageId": "up-next"
        }
      ]
    },
    {
      "type": "blocker",
      "title": "GAUSSIAN is expensive and restrictive.",
      "stage": "short-term",
      "swimlaneId": "md-modeling",
      "id": "gn5dErnDbvGi257f3TGAs",
      "itemLastUpdated": "2026-01-14T19:42:01.786Z",
      "description": "Mike will reach out to Phenix people to see what they have been working on instead for this. ",
      "blockerStatus": "open"
    },
    {
      "type": "milestone",
      "title": "Establish regular standing meeting with Kara, Steve",
      "stage": "short-term",
      "swimlaneId": "data-acquisition",
      "id": "m-NV3wzdXJKZ11wwnLPsa",
      "itemLastUpdated": "2026-01-14T19:44:52.686Z"
    },
    {
      "type": "milestone",
      "title": "Sampleworks: Pipeline can accept experimental data and generative models",
      "stage": "short-term",
      "swimlaneId": "ml-modeling",
      "id": "SWMeaLPpdXDDWtSmzLH58",
      "itemLastUpdated": "2026-01-14T19:48:54.613Z",
      "description": ""
    },
    {
      "type": "milestone",
      "title": "Sampleworks: Ability to do guided sampling of ensembles, providing output model with corresponding metrics",
      "stage": "short-term",
      "swimlaneId": "ml-modeling",
      "id": "eRNApCCbjA9apUPXvL9PD",
      "itemLastUpdated": "2026-01-14T19:48:35.643Z",
      "description": ""
    },
    {
      "type": "output",
      "title": "Sampleworks: Initial water generative model benchmarked against experimental data",
      "stage": "short-term",
      "swimlaneId": "ml-modeling",
      "id": "guYYyLmu4EQkVEKsORIuB",
      "itemLastUpdated": "2026-01-14T19:52:34.145Z",
      "description": ""
    },
    {
      "type": "blocker",
      "title": "Scaling issues with refactoring and API calls",
      "stage": "recent",
      "swimlaneId": "ml-modeling",
      "id": "OmRI4qAqyZMa-OICrSa4x",
      "itemLastUpdated": "2026-01-14T19:50:21.597Z",
      "blockerStatus": "resolved",
      "subItems": [
        {
          "id": "Rn-hvDvTujKop6_H9W1uE",
          "title": "Refactoring guidance scripts enables us to run continuously without reloading models",
          "completed": true,
          "order": 0,
          "subStageId": "backlog"
        },
        {
          "id": "TORG5rAqF806gkAmvONtG",
          "title": "Reduced API calls, avoid throttling for MSAs by creating a local on-disk cache.",
          "completed": true,
          "order": 1,
          "subStageId": "backlog"
        }
      ],
      "subItemConfig": {
        "viewType": "tasks",
        "customStages": [
          {
            "id": "done",
            "label": "Done",
            "order": 0
          },
          {
            "id": "in-progress",
            "label": "In Progress",
            "order": 1
          },
          {
            "id": "up-next",
            "label": "Up Next",
            "order": 2
          },
          {
            "id": "backlog",
            "label": "Backlog",
            "order": 3
          }
        ],
        "customStatusTags": [
          {
            "id": "not-started",
            "label": "Not Started",
            "color": "#6B7280"
          },
          {
            "id": "in-progress",
            "label": "In Progress",
            "color": "#3B82F6"
          },
          {
            "id": "blocked",
            "label": "Blocked",
            "color": "#EF4444"
          },
          {
            "id": "in-review",
            "label": "In Review",
            "color": "#F59E0B"
          },
          {
            "id": "done",
            "label": "Done",
            "color": "#10B981"
          }
        ]
      },
      "description": ""
    },
    {
      "type": "output",
      "title": "Sampleworks: Test 40 structure dataset",
      "stage": "short-term",
      "swimlaneId": "ml-modeling",
      "id": "tX5-R9AThl8QfX_ZGLnvb",
      "itemLastUpdated": "2026-01-14T19:52:28.532Z",
      "description": ""
    },
    {
      "type": "milestone",
      "title": "Sampleworks: Implemented RSCC for maps computed from sampled conformers",
      "stage": "recent",
      "swimlaneId": "ml-modeling",
      "id": "9U08e_xH2KZPEntrjosXC",
      "itemLastUpdated": "2026-01-14T19:49:39.263Z",
      "completed": true
    },
    {
      "type": "output",
      "title": "Sampleworks: Clustering conformers based on LDDT. Comparing cluster sizes to experimental occupancy, LDDT to nearest altloc.",
      "stage": "short-term",
      "swimlaneId": "ml-modeling",
      "id": "mBAUOxUXq7MYx9x8t5GN4",
      "itemLastUpdated": "2026-01-14T19:50:11.693Z",
      "links": [
        {
          "url": "https://docs.google.com/presentation/d/1_K_YZy8HRRqBXtKjI1603MV0NDKyU_x84DzRYyci-qQ/edit?slide=id.g3b5e85cd564_3_5&pli=1#slide=id.g3b5e85cd564_3_5",
          "label": "Initial LDDT clustering results",
          "type": "gdoc",
          "id": "aPpFS_rN3s3ZAwgEDNE3c"
        }
      ]
    },
    {
      "type": "milestone",
      "title": "⭐ Sampleworks comprehensive tests",
      "stage": "long-term",
      "swimlaneId": "ml-modeling",
      "id": "6rr_BRKWcxEGiMtZ1Cp0a",
      "itemLastUpdated": "2026-01-14T19:52:38.113Z"
    },
    {
      "type": "milestone",
      "title": "⭐Sampleworks: refactoring model sampling/guidance",
      "stage": "long-term",
      "swimlaneId": "ml-modeling",
      "id": "AGHICqDv4Mz8V3EC7rIwo",
      "itemLastUpdated": "2026-01-14T19:52:39.012Z"
    },
    {
      "type": "milestone",
      "title": "⭐Sampleworks: generalizing the reward functions for future usage with multiple experimental modalities",
      "stage": "long-term",
      "swimlaneId": "ml-modeling",
      "id": "U5j55q4gyr7ec40X2lFdr",
      "itemLastUpdated": "2026-01-14T19:52:39.912Z"
    },
    {
      "type": "blocker",
      "title": "Water modeling requires multiple VP GPUs",
      "stage": "short-term",
      "swimlaneId": "ml-modeling",
      "id": "hPyAjdULHa0q7zMvj7up0",
      "itemLastUpdated": "2026-01-14T19:53:28.970Z",
      "blockerStatus": "open"
    },
    {
      "type": "milestone",
      "title": "mmCIF working group meeting",
      "stage": "short-term",
      "swimlaneId": "encoding",
      "id": "cIxC7AUjNxBCWZW7il-HX",
      "itemLastUpdated": "2026-01-14T19:54:07.392Z"
    },
    {
      "type": "milestone",
      "title": "Figured out path to adding GUI extension to coot 1.0+",
      "stage": "recent",
      "swimlaneId": "encoding",
      "id": "Wbie6_kEUSpVZ8r6GRTzP",
      "itemLastUpdated": "2026-01-14T19:54:25.672Z",
      "completed": true,
      "isWin": true
    },
    {
      "type": "milestone",
      "title": "Workflow outlining for generating hierarchical models from multiconformer models",
      "stage": "short-term",
      "swimlaneId": "encoding",
      "id": "I6OXfOYEOr4CP3mm-FwOt",
      "itemLastUpdated": "2026-01-14T19:54:34.779Z"
    },
    {
      "type": "milestone",
      "title": "Gemmi integration",
      "stage": "short-term",
      "swimlaneId": "encoding",
      "id": "9DD-SI2RiBxW3LStoHdGX",
      "itemLastUpdated": "2026-01-14T19:54:47.438Z"
    }
  ]
}